cloudmonitor/__init__.py
cloudmonitor/__main__.py
cloudmonitor/config.py
cloudmonitor/main.py
cloudmonitor/server.py
cloudmonitor/gpu/__init__.py
cloudmonitor/gpu/define.py
cloudmonitor/gpu/query.py
cloudmonitor/ssh/__init__.py
cloudmonitor/ssh/client.py
cloudmonitor/status/__init__.py
cloudmonitor/status/define.py
cloudmonitor/status/query.py
cloudmonitor/templates/index.html
cloudmonitor-1.0.0.0.dist-info/METADATA
cloudmonitor-1.0.0.0.dist-info/WHEEL
cloudmonitor-1.0.0.0.dist-info/entry_points.txt
cloudmonitor-1.0.0.0.dist-info/top_level.txt
cloudmonitor-1.0.0.0.dist-info/RECORD
