Metadata-Version: 2.1
Name: cloudmonitor
Version: 1.0.0.0
Summary: A Web-GUI Monitor for Academic Linux Servers
Home-page: https://github.com/WNJXYK/cloudmonitor
Author: Zhi Zhou
Author-email: wnjxyk@gmail.com
License: MIT Licence
Classifier: Intended Audience :: Science/Research
Classifier: Intended Audience :: Developers
Classifier: Programming Language :: Python
Classifier: Topic :: Software Development
Classifier: Topic :: Scientific/Engineering
Classifier: Operating System :: POSIX :: Linux
Classifier: Operating System :: Microsoft :: Windows
Classifier: Operating System :: MacOS
Classifier: Programming Language :: Python :: 3.6
Classifier: Programming Language :: Python :: 3.7
Classifier: Programming Language :: Python :: 3.8
Requires-Python: >=3.6.0
Requires-Dist: flask (>=2.0.0)
Requires-Dist: paramiko (>=3.0.0)
Requires-Dist: pyyaml (>=6.0)
Requires-Dist: gevent (>=22.10.2)
